bout_runners/__init__.py
bout_runners/configure_bout_runners.py
bout_runners/config/__init__.py
bout_runners/config/bout_runners.ini
bout_runners/config/logging_config.yaml
bout_runners/database/__init__.py
bout_runners/database/database_connector.py
bout_runners/database/database_creator.py
bout_runners/database/database_reader.py
bout_runners/database/database_utils.py
bout_runners/database/database_writer.py
bout_runners/executor/__init__.py
bout_runners/executor/bout_paths.py
bout_runners/executor/executor.py
bout_runners/log/__init__.py
bout_runners/log/log_reader.py
bout_runners/make/__init__.py
bout_runners/make/make.py
bout_runners/make/read_makefile.py
bout_runners/metadata/__init__.py
bout_runners/metadata/metadata_reader.py
bout_runners/metadata/metadata_recorder.py
bout_runners/metadata/metadata_updater.py
bout_runners/metadata/status_checker.py
bout_runners/parameters/__init__.py
bout_runners/parameters/default_parameters.py
bout_runners/parameters/final_parameters.py
bout_runners/parameters/run_parameters.py
bout_runners/runner/__init__.py
bout_runners/runner/bout_runner.py
bout_runners/submitter/__init__.py
bout_runners/submitter/abstract_submitter.py
bout_runners/submitter/local_submitter.py
bout_runners/submitter/processor_split.py
bout_runners/submitter/submitter_factory.py
bout_runners/utils/__init__.py
bout_runners/utils/file_operations.py
bout_runners/utils/logs.py
bout_runners/utils/names.py
bout_runners/utils/paths.py
docs/source/__init__.py
docs/source/conf.py
tests/integration/__init__.py
tests/integration/bout_runners/__init__.py
tests/integration/bout_runners/runners/__init__.py
tests/integration/bout_runners/runners/test_runner.py
tests/unit/__init__.py
tests/unit/bout_runners/__init__.py
tests/unit/bout_runners/test_configure_bout_runners.py
tests/unit/bout_runners/database/__init__.py
tests/unit/bout_runners/database/test_database_connector.py
tests/unit/bout_runners/database/test_database_creator.py
bout_runners-2.0.0a3.dist-info/LICENSE
bout_runners-2.0.0a3.dist-info/METADATA
bout_runners-2.0.0a3.dist-info/WHEEL
bout_runners-2.0.0a3.dist-info/entry_points.txt
bout_runners-2.0.0a3.dist-info/top_level.txt
bout_runners-2.0.0a3.dist-info/RECORD
