Metadata-Version: 2.1
Name: bout-runners
Version: 2.0.0a3
Summary: Manage your BOUT++ runs through python
Home-page: https://github.com/CELMA-project/bout_runners
Author: Michael Løiten
Author-email: michael.l.magnussen@gmail.com
Maintainer: Michael Løiten
Maintainer-email: michael.l.magnussen@gmail.com
License: GNU Lesser General Public License v3 or later (LGPLv3+)
Keywords: bout++,plasma,metadata recorder,numerical simulation
Platform: UNKNOWN
Classifier: Development Status :: 3 - Alpha
Classifier: Intended Audience :: Science/Research
Classifier: License :: OSI Approved :: GNU Lesser General Public License v3 or later (LGPLv3+)
Classifier: Operating System :: OS Independent
Classifier: Programming Language :: Python
Classifier: Programming Language :: Python :: 3
Classifier: Programming Language :: Python :: 3.6
Classifier: Programming Language :: Python :: 3.7
Classifier: Programming Language :: Python :: 3.8
Classifier: Topic :: Scientific/Engineering :: Physics
Classifier: Topic :: System :: Distributed Computing
Requires-Python: >=3.6
Requires-Dist: pyyaml (>=5.1.2)
Requires-Dist: numpy (>=1.17.4)
Requires-Dist: pandas (>=0.25.3)
Requires-Dist: psutil (>=5.7.0)
Provides-Extra: dev
Requires-Dist: pre-commit (>=2.4.0) ; extra == 'dev'
Provides-Extra: docs
Requires-Dist: numpydoc (>=1.0.0) ; extra == 'docs'
Requires-Dist: sphinx (>=3.0.4) ; extra == 'docs'
Provides-Extra: fast
Requires-Dist: numexpr (>=2.7.0) ; extra == 'fast'
Requires-Dist: Bottleneck (>=1.3.1) ; extra == 'fast'
Provides-Extra: test
Requires-Dist: pytest (>=5.3.0) ; extra == 'test'
Requires-Dist: pytest-timeout (>=1.3.4) ; extra == 'test'
